docassemble_flask_user/__init__.py
docassemble_flask_user/access.py
docassemble_flask_user/db_adapters.py
docassemble_flask_user/decorators.py
docassemble_flask_user/emails.py
docassemble_flask_user/forms.py
docassemble_flask_user/passwords.py
docassemble_flask_user/settings.py
docassemble_flask_user/signals.py
docassemble_flask_user/tokens.py
docassemble_flask_user/translations.py
docassemble_flask_user/views.py
docassemble_flask_user/templates/base.html
docassemble_flask_user/templates/flask_user/_macros.html
docassemble_flask_user/templates/flask_user/change_password.html
docassemble_flask_user/templates/flask_user/change_username.html
docassemble_flask_user/templates/flask_user/flask_user_base.html
docassemble_flask_user/templates/flask_user/forgot_password.html
docassemble_flask_user/templates/flask_user/invite.html
docassemble_flask_user/templates/flask_user/login.html
docassemble_flask_user/templates/flask_user/login_or_register.html
docassemble_flask_user/templates/flask_user/manage_emails.html
docassemble_flask_user/templates/flask_user/member_base.html
docassemble_flask_user/templates/flask_user/public_base.html
docassemble_flask_user/templates/flask_user/register.html
docassemble_flask_user/templates/flask_user/resend_confirm_email.html
docassemble_flask_user/templates/flask_user/reset_password.html
docassemble_flask_user/templates/flask_user/user_profile.html
docassemble_flask_user/templates/flask_user/emails/base_message.html
docassemble_flask_user/templates/flask_user/emails/base_message.txt
docassemble_flask_user/templates/flask_user/emails/base_subject.txt
docassemble_flask_user/templates/flask_user/emails/confirm_email_message.html
docassemble_flask_user/templates/flask_user/emails/confirm_email_message.txt
docassemble_flask_user/templates/flask_user/emails/confirm_email_subject.txt
docassemble_flask_user/templates/flask_user/emails/forgot_password_message.html
docassemble_flask_user/templates/flask_user/emails/forgot_password_message.txt
docassemble_flask_user-0.6.31.dist-info/licenses/AUTHORS.rst
docassemble_flask_user-0.6.31.dist-info/licenses/LICENSE.txt
docassemble_flask_user-0.6.31.dist-info/METADATA
docassemble_flask_user-0.6.31.dist-info/WHEEL
docassemble_flask_user-0.6.31.dist-info/top_level.txt
docassemble_flask_user-0.6.31.dist-info/RECORD
