Metadata-Version: 2.4
Name: Docassemble-Flask-User
Version: 0.6.31
Summary: Customizable User Authentication and Management, and more.
Home-page: http://github.com/jhpyle/Flask-User
Author: Ling Thio, Jonathan Pyle
Author-email: jhpyle@gmail.com
License: BSD License
Keywords: Flask User Registration Email Username Confirmation Password Reset
Platform: any
Classifier: Development Status :: 5 - Production/Stable
Classifier: Environment :: Web Environment
Classifier: Framework :: Flask
Classifier: Intended Audience :: Developers
Classifier: License :: OSI Approved :: BSD License
Classifier: Natural Language :: Chinese (Simplified)
Classifier: Natural Language :: Dutch
Classifier: Natural Language :: English
Classifier: Natural Language :: German
Classifier: Natural Language :: Spanish
Classifier: Natural Language :: Finnish
Classifier: Natural Language :: French
Classifier: Natural Language :: Italian
Classifier: Natural Language :: Persian
Classifier: Natural Language :: Russian
Classifier: Natural Language :: Swedish
Classifier: Natural Language :: Turkish
Classifier: Operating System :: OS Independent
Classifier: Programming Language :: Python
Classifier: Programming Language :: Python :: 2.6
Classifier: Programming Language :: Python :: 2.7
Classifier: Programming Language :: Python :: 3.3
Classifier: Programming Language :: Python :: 3.4
Classifier: Programming Language :: Python :: 3.5
Classifier: Programming Language :: Python :: 3.6
Classifier: Topic :: Internet :: WWW/HTTP :: Dynamic Content
Classifier: Topic :: Security
Classifier: Topic :: Software Development :: Libraries :: Python Modules
Requires-Python: >=2.6, !=3.0.*, !=3.1.*, !=3.2.*
License-File: LICENSE.txt
License-File: AUTHORS.rst
Requires-Dist: bcrypt
Requires-Dist: Flask
Requires-Dist: Flask-Login
Requires-Dist: Flask-Mail
Requires-Dist: Flask-SQLAlchemy
Requires-Dist: Flask-WTF
Requires-Dist: pwdlib
Requires-Dist: pycryptodome
Dynamic: author
Dynamic: author-email
Dynamic: classifier
Dynamic: description
Dynamic: home-page
Dynamic: keywords
Dynamic: license
Dynamic: license-file
Dynamic: platform
Dynamic: requires-dist
Dynamic: requires-python
Dynamic: summary
